MANIFEST.in
README.rst
setup.py
docs/HISTORY.txt
wcs/__init__.py
wcs.adminauth.egg-info/PKG-INFO
wcs.adminauth.egg-info/SOURCES.txt
wcs.adminauth.egg-info/dependency_links.txt
wcs.adminauth.egg-info/entry_points.txt
wcs.adminauth.egg-info/namespace_packages.txt
wcs.adminauth.egg-info/not-zip-safe
wcs.adminauth.egg-info/requires.txt
wcs.adminauth.egg-info/top_level.txt
wcs/adminauth/__init__.py
wcs/adminauth/auth.py
wcs/adminauth/configure.zcml
wcs/adminauth/session.py
wcs/adminauth/session.zpt
wcs/adminauth/testing.py
wcs/adminauth/tests/__init__.py
wcs/adminauth/tests/test_auth.py
wcs/adminauth/tests/test_session.py
wcs/adminauth/tests/utils.py
wcs/adminauth/tests/data/service_validate_invalid_ticket.xml
wcs/adminauth/tests/data/service_validate_success.xml