Metadata-Version: 2.1
Name: wcs.adminauth
Version: 1.0.1
Summary: Administrative login for Plone sites using CAS.
Home-page: https://github.com/webcloud7/wcs.adminauth
Author: webcloud7 ag
Author-email: mailto:m.leimgruber@webcloud7.ch
License: GPL2
Classifier: Framework :: Plone
Classifier: Framework :: Plone :: 6.0
Classifier: Framework :: Plone :: 5.1
Classifier: Framework :: Plone :: 5.2
Classifier: Programming Language :: Python
Classifier: Programming Language :: Python :: 2.7
Classifier: Programming Language :: Python :: 3.11
Classifier: Intended Audience :: Developers
Classifier: Topic :: Software Development :: Libraries :: Python Modules
Provides-Extra: tests
